__init__.py
py_console/__init__.py
py_console/console.py
py_console/definitions.py
py_console-0.1.6.dist-info/METADATA
py_console-0.1.6.dist-info/WHEEL
py_console-0.1.6.dist-info/license.txt
py_console-0.1.6.dist-info/top_level.txt
py_console-0.1.6.dist-info/RECORD
