Metadata-Version: 2.1
Name: py-console
Version: 0.1.6
Summary: Colorful JavaScript-like console logging
Author-email: Mike=Huls <mikehuls42@gmail.com>
Project-URL: Homepage, https://bitbucket.org/LeadQ/dnxlogger
Project-URL: Bug Tracker, https://github.com/mike-huls/py-console/issues
Classifier: Programming Language :: Python :: 3
Classifier: License :: OSI Approved :: MIT License
Classifier: Operating System :: OS Independent
Requires-Python: >=3.9
License-File: license.txt
Requires-Dist: colorama
